django_admin_range/__init__.py
django_admin_range/apps.py
django_admin_range/filters.py
django_admin_range/locale/af/LC_MESSAGES/django.mo
django_admin_range/locale/af/LC_MESSAGES/django.po
django_admin_range/locale/ar/LC_MESSAGES/django.mo
django_admin_range/locale/ar/LC_MESSAGES/django.po
django_admin_range/locale/az/LC_MESSAGES/django.mo
django_admin_range/locale/az/LC_MESSAGES/django.po
django_admin_range/locale/be/LC_MESSAGES/django.mo
django_admin_range/locale/be/LC_MESSAGES/django.po
django_admin_range/locale/bg/LC_MESSAGES/django.mo
django_admin_range/locale/bg/LC_MESSAGES/django.po
django_admin_range/locale/ca/LC_MESSAGES/django.mo
django_admin_range/locale/ca/LC_MESSAGES/django.po
django_admin_range/locale/cs/LC_MESSAGES/django.mo
django_admin_range/locale/cs/LC_MESSAGES/django.po
django_admin_range/locale/da/LC_MESSAGES/django.mo
django_admin_range/locale/da/LC_MESSAGES/django.po
django_admin_range/locale/de/LC_MESSAGES/django.mo
django_admin_range/locale/de/LC_MESSAGES/django.po
django_admin_range/locale/el/LC_MESSAGES/django.mo
django_admin_range/locale/el/LC_MESSAGES/django.po
django_admin_range/locale/en/LC_MESSAGES/django.mo
django_admin_range/locale/en/LC_MESSAGES/django.po
django_admin_range/locale/en-au/LC_MESSAGES/django.mo
django_admin_range/locale/en-au/LC_MESSAGES/django.po
django_admin_range/locale/en-gb/LC_MESSAGES/django.mo
django_admin_range/locale/en-gb/LC_MESSAGES/django.po
django_admin_range/locale/es/LC_MESSAGES/django.mo
django_admin_range/locale/es/LC_MESSAGES/django.po
django_admin_range/locale/es-ar/LC_MESSAGES/django.mo
django_admin_range/locale/es-ar/LC_MESSAGES/django.po
django_admin_range/locale/es-co/LC_MESSAGES/django.mo
django_admin_range/locale/es-co/LC_MESSAGES/django.po
django_admin_range/locale/es-mx/LC_MESSAGES/django.mo
django_admin_range/locale/es-mx/LC_MESSAGES/django.po
django_admin_range/locale/et/LC_MESSAGES/django.mo
django_admin_range/locale/et/LC_MESSAGES/django.po
django_admin_range-0.1.9.dist-info/licenses/LICENSE
django_admin_range-0.1.9.dist-info/METADATA
django_admin_range-0.1.9.dist-info/WHEEL
django_admin_range-0.1.9.dist-info/top_level.txt
django_admin_range-0.1.9.dist-info/RECORD
