Metadata-Version: 2.4
Name: django-admin-range
Version: 0.1.9
Summary: Reusable date, datetime, and numeric range filters for Django admin in new UI style. Compatible with Django's default admin, Jazzmin, and Grappelli admin interfaces.
Author-email: Isa Arifoglu <arifogluisa@gmail.com>
License: MIT
Project-URL: Homepage, https://github.com/arifogluisa/django-admin-range
Project-URL: Repository, https://github.com/arifogluisa/django-admin-range
Classifier: Development Status :: 5 - Production/Stable
Classifier: Environment :: Web Environment
Classifier: Intended Audience :: Developers
Classifier: Framework :: Django
Classifier: Framework :: Django :: 3.2
Classifier: Framework :: Django :: 4
Classifier: Framework :: Django :: 4.0
Classifier: Framework :: Django :: 4.1
Classifier: Framework :: Django :: 4.2
Classifier: Framework :: Django :: 5
Classifier: Framework :: Django :: 5.0
Classifier: Framework :: Django :: 5.1
Classifier: Framework :: Django :: 5.2
Classifier: Framework :: Django :: 6.0
Classifier: Programming Language :: Python :: 3.9
Classifier: Programming Language :: Python :: 3.10
Classifier: Programming Language :: Python :: 3.11
Classifier: Programming Language :: Python :: 3.12
Classifier: Programming Language :: Python :: 3.13
Classifier: Programming Language :: Python :: 3.14
Classifier: License :: OSI Approved :: MIT License
Classifier: Operating System :: OS Independent
Classifier: Topic :: Utilities
Requires-Python: >=3.9
License-File: LICENSE
Requires-Dist: django>=3.2
Dynamic: license-file
